j40_model/__init__.py
j40_model/aux_functions.py
j40_model/community_case.py
j40_model/interventions.py
j40_model/nomenclature.py
j40_model/optimization_model.py
j40_model/simulation_heuristic.py
j40model-1.1.1.dist-info/LICENSE
j40model-1.1.1.dist-info/METADATA
j40model-1.1.1.dist-info/WHEEL
j40model-1.1.1.dist-info/top_level.txt
j40model-1.1.1.dist-info/RECORD
