Metadata-Version: 2.1
Name: j40model
Version: 1.1.1
Summary: Base simulation and optimization modules for J40 tool
Home-page: https://github.com/LBNLgrid/j40model
Author: Miguel Heleno
Author-email: miguelhelenoa@lbl.gov
License-File: LICENSE
Requires-Dist: geopandas
Requires-Dist: numpy
Requires-Dist: pandas
Requires-Dist: Pyomo
